README
setup.py
foursquare.pants.rules.egg-info/PKG-INFO
foursquare.pants.rules.egg-info/SOURCES.txt
foursquare.pants.rules.egg-info/dependency_links.txt
foursquare.pants.rules.egg-info/entry_points.txt
foursquare.pants.rules.egg-info/namespace_packages.txt
foursquare.pants.rules.egg-info/top_level.txt
foursquare/pants/rules/__init__.py
foursquare/pants/rules/register.py
foursquare/pants/rules/tag.py
foursquare/pants/rules/validate.py