Metadata-Version: 1.1
Name: foursquare.pants.rules
Version: 0.0.1
Summary: BUILD graph validate rules plugin for pants build
Home-page: https://github.com/foursquare/pants-rules
Author: Foursquare
Author-email: pants@foursquare.com
License: UNKNOWN
Download-URL: https://github.com/foursquare/pants-rules/tags/v0.0.1
Keywords: pantsbuild,pantsbuild plugin,BUILD graph
Platform: UNKNOWN
